dlmslib/__init__.py
dlmslib/utils.py
dlmslib/keras_models/__init__.py
dlmslib/keras_models/layers.py
dlmslib/keras_models/nlp_models.py
dlmslib/torch_models/__init__.py
dlmslib/torch_models/demos.py
dlmslib/torch_models/nlp_models.py
dlmslib/torch_models/trees.py
tests/__init__.py
tests/dlmslib/__init__.py
tests/dlmslib/keras_models/__init__.py
tests/dlmslib/keras_models/nlp_models_tests.py
tests/dlmslib/keras_models/test_nlp_models.py
tests/dlmslib/torch_models/__init__.py
tests/dlmslib/torch_models/nlp_models_tests.py
tests/dlmslib/torch_models/trees_test.py
dlmslib-0.45.dist-info/LICENSE
dlmslib-0.45.dist-info/METADATA
dlmslib-0.45.dist-info/WHEEL
dlmslib-0.45.dist-info/top_level.txt
dlmslib-0.45.dist-info/zip-safe
dlmslib-0.45.dist-info/RECORD
